termdo/__init__.py
termdo/__main__.py
termdo/cli.py
termdo-1.0.0.dist-info/METADATA
termdo-1.0.0.dist-info/WHEEL
termdo-1.0.0.dist-info/entry_points.txt
termdo-1.0.0.dist-info/top_level.txt
termdo-1.0.0.dist-info/RECORD
