Metadata-Version: 2.4
Name: termdo
Version: 1.0.0
Summary: A terminal-based todo app with colored output, categories and priorities
Author: Akash Nandy
Requires-Python: >=3.8
Requires-Dist: rich>=12.0.0
